yet_another_hello_pypi/__init__.py
yet_another_hello_pypi/say_hello.py
yet_another_hello_pypi-0.0.2.dist-info/METADATA
yet_another_hello_pypi-0.0.2.dist-info/WHEEL
yet_another_hello_pypi-0.0.2.dist-info/top_level.txt
yet_another_hello_pypi-0.0.2.dist-info/RECORD
