Metadata-Version: 2.2
Name: yet_another_hello_pypi
Version: 0.0.2
Summary: An example Python package deployed to PyPI
Home-page: https://github.com/pygumby/yet_another_hello_pypi
Author: pygumby
Classifier: Programming Language :: Python :: 3
Classifier: License :: OSI Approved :: MIT License
Classifier: Operating System :: OS Independent
Requires-Python: >=3.6
Dynamic: author
Dynamic: classifier
Dynamic: description
Dynamic: description-content-type
Dynamic: home-page
Dynamic: requires-python
Dynamic: summary
